onnx_web/__init__.py
onnx_web/constants.py
onnx_web/errors.py
onnx_web/logging.py
onnx_web/main.py
onnx_web/output.py
onnx_web/params.py
onnx_web/torch_before_ort.py
onnx_web/utils.py
onnx_web/chain/__init__.py
onnx_web/chain/base.py
onnx_web/chain/blend_denoise_fastnlmeans.py
onnx_web/chain/blend_denoise_localstd.py
onnx_web/chain/blend_grid.py
onnx_web/chain/blend_img2img.py
onnx_web/chain/blend_linear.py
onnx_web/chain/blend_mask.py
onnx_web/chain/correct_codeformer.py
onnx_web/chain/correct_gfpgan.py
onnx_web/chain/highres.py
onnx_web/chain/persist_disk.py
onnx_web/chain/persist_s3.py
onnx_web/chain/pipeline.py
onnx_web/chain/reduce_crop.py
onnx_web/chain/reduce_thumbnail.py
onnx_web/chain/result.py
onnx_web/chain/source_noise.py
onnx_web/chain/source_s3.py
onnx_web/chain/source_txt2img.py
onnx_web/chain/source_url.py
onnx_web/chain/stages.py
onnx_web/chain/tile.py
onnx_web/chain/upscale.py
onnx_web/chain/upscale_bsrgan.py
onnx_web/chain/upscale_highres.py
onnx_web/chain/upscale_outpaint.py
onnx_web/chain/upscale_resrgan.py
onnx_web/chain/upscale_simple.py
onnx_web/chain/upscale_stable_diffusion.py
onnx_web/chain/upscale_swinir.py
onnx_web/image/__init__.py
onnx_web/image/ade_palette.py
onnx_web/image/laion_face.py
onnx_web/image/mask_filter.py
onnx_web/image/noise_source.py
onnx_web/image/source_filter.py
onnx_web/image/utils.py
onnx_web/onnx/__init__.py
onnx_web/onnx/onnx_net.py
onnx_web/server/__init__.py
onnx_web/server/admin.py
onnx_web/server/api.py
onnx_web/server/context.py
onnx_web/server/hacks.py
onnx_web/server/load.py
onnx_web/server/model_cache.py
onnx_web/server/params.py
onnx_web/server/plugin.py
onnx_web/server/static.py
onnx_web/server/utils.py
onnx_web/worker/__init__.py
onnx_web/worker/command.py
onnx_web/worker/context.py
onnx_web/worker/logging.py
onnx_web/worker/pool.py
onnx_web/worker/utils.py
onnx_web/worker/worker.py
onnx_web-0.12.0.dist-info/METADATA
onnx_web-0.12.0.dist-info/WHEEL
onnx_web-0.12.0.dist-info/top_level.txt
onnx_web-0.12.0.dist-info/RECORD
